owl_on_fhir/__init__.py
owl_on_fhir/__main__.py
owl_on_fhir/convert_owl_ncbo2owl.pl
owl_on_fhir/favorites.py
owl_on_fhir/robot.jar
owl_on_fhir-1.1.5.dist-info/METADATA
owl_on_fhir-1.1.5.dist-info/WHEEL
owl_on_fhir-1.1.5.dist-info/entry_points.txt
owl_on_fhir-1.1.5.dist-info/top_level.txt
owl_on_fhir-1.1.5.dist-info/RECORD
