Metadata-Version: 2.1
Name: owl-on-fhir
Version: 1.1.5
Summary: Python-based non-minimalistic OWL to FHIR converter.
Home-page: https://github.com/HOT-Ecosystem/owl-on-fhir/
Author: Joe Flack
Author-email: jflack@jhu.edu
Classifier: License :: OSI Approved :: MIT License
Classifier: Programming Language :: Python
Classifier: Programming Language :: Python :: 3
Classifier: Programming Language :: Python :: 3.9
Classifier: Programming Language :: Python :: 3.10
Classifier: Programming Language :: Python :: 3.11
Classifier: Programming Language :: Python :: 3.12
Classifier: Programming Language :: Python :: Implementation :: CPython
Classifier: Programming Language :: Python :: Implementation :: PyPy
Requires-Python: >=3.9.0
Requires-Dist: bioontologies ==0.2.1
Requires-Dist: oaklib >=0.5.1
Requires-Dist: requests >2.28.2
Requires-Dist: sssom ==0.3.28
